morpholog/__init__.py
morpholog/map.pickle
morpholog/morpholog.py
morpholog-1.6.dist-info/METADATA
morpholog-1.6.dist-info/WHEEL
morpholog-1.6.dist-info/top_level.txt
morpholog-1.6.dist-info/RECORD
