Metadata-Version: 2.1
Name: morpholog
Version: 1.6
Summary: Morphological tokenizer for Russian is able to split words into morphemes: prefixes, roots, infixes, suffix and postfixes
Home-page: https://github.com/constantin50/morpholog
Author: Constantin Werner
Author-email: const.werner@gmail.com
License: MIT
Keywords: tokenizer,morphemes,NLP,russian
Platform: UNKNOWN
Classifier: Programming Language :: Python :: 3
Classifier: License :: OSI Approved :: MIT License
Classifier: Operating System :: OS Independent
